pexen/__init__.py
pexen/util.py
pexen/factory/__init__.py
pexen/factory/base.py
pexen/factory/filesystem.py
pexen/factory/modtree.py
pexen/factory/module.py
pexen/sched/__init__.py
pexen/sched/common.py
pexen/sched/meta.py
pexen/sched/planner.py
pexen/sched/pool.py
pexen-0.0.3.dist-info/LICENSE
pexen-0.0.3.dist-info/METADATA
pexen-0.0.3.dist-info/WHEEL
pexen-0.0.3.dist-info/top_level.txt
pexen-0.0.3.dist-info/RECORD
