Metadata-Version: 2.1
Name: pexen
Version: 0.0.3
Summary: Python EXecution ENvironment, scheduler included
Home-page: https://github.com/comps/pexen
Author: Jiri Jaburek
Author-email: comps@nomail.dom
License: UNKNOWN
Platform: UNKNOWN
Classifier: Development Status :: 3 - Alpha
Classifier: Intended Audience :: Developers
Classifier: Programming Language :: Python :: 3 :: Only
Classifier: License :: OSI Approved :: MIT License
Classifier: Operating System :: OS Independent
